MANIFEST.in
README.md
setup.cfg
setup.py
phantom_cli.egg-info/PKG-INFO
phantom_cli.egg-info/SOURCES.txt
phantom_cli.egg-info/dependency_links.txt
phantom_cli.egg-info/entry_points.txt
phantom_cli.egg-info/not-zip-safe
phantom_cli.egg-info/requires.txt
phantom_cli.egg-info/top_level.txt
phantomcli/__init__.py
phantomcli/_util.py
phantomcli/command.py
phantomcli/data.py
phantomcli/image.py
phantomcli/network.py
phantomcli/phantom.py
phantomcli/sample.jpg
phantomcli/scripts/__init__.py
phantomcli/scripts/phdiscover.py
phantomcli/scripts/phget.py
phantomcli/scripts/phgetall.py
phantomcli/scripts/phimg.py
phantomcli/scripts/phmock.py
phantomcli/scripts/phmode.py
phantomcli/scripts/phset.py
phantomcli/scripts/phtest.py
phantomcli/scripts/util.py
phantomcli/tests/__init__.py
phantomcli/tests/sample.jpg
phantomcli/tests/test_image.py
phantomcli/tests/test_network.py