Metadata-Version: 1.2
Name: phantom-cli
Version: 0.0.0.19
Summary: command line tools to interact with the phantom camera
Home-page: https://github.com/the16thpythonist/phantom-cli
Author: Jonas Teufel
Author-email: jonseb1998@gmail.com
License: MIT
Platform: UNKNOWN
Requires-Python: ~=3.5
